pyoneai/__init__.py
pyoneai/config.py
pyoneai/session.py
pyoneai/core/__init__.py
pyoneai/core/bases.py
pyoneai/core/cluster.py
pyoneai/core/const.py
pyoneai/core/datastore.py
pyoneai/core/errors.py
pyoneai/core/group.py
pyoneai/core/host.py
pyoneai/core/image.py
pyoneai/core/metric.py
pyoneai/core/metric_accessors.py
pyoneai/core/metric_collection.py
pyoneai/core/one.py
pyoneai/core/pci_device.py
pyoneai/core/predictor.py
pyoneai/core/service.py
pyoneai/core/time_index.py
pyoneai/core/user.py
pyoneai/core/virtual_machine.py
pyoneai/core/virtual_network.py
pyoneai/core/vm_template_data.py
pyoneai/drivers/xmlrpc.py
pyoneai/mlmodels/__init__.py
pyoneai/mlmodels/arima_model.py
pyoneai/mlmodels/identity_model.py
pyoneai/mlmodels/lstm_model.py
pyoneai/mlmodels/persistence_model.py
pyoneai/mlmodels/transformer_model.py
pyoneai/mlmodels/utils/__init__.py
pyoneai/mlmodels/utils/model_loader.py
pyoneai/mlmodels/utils/prediction_utils.py
pyoneai/registry/__init__.py
pyoneai/registry/registry.py
pyoneai/tests/integration/conftest.py
pyoneai/tests/integration/test_pyoneai_sdk.py
pyoneai/tests/unit/__init__.py
pyoneai/tests/unit/conftest.py
pyoneai/tests/unit/test_arima_model.py
pyoneai/tests/unit/test_config.py
pyoneai/tests/unit/test_session.py
pyoneai/tests/unit/test_core/test_bases.py
pyoneai/tests/unit/test_core/test_cluster.py
pyoneai/tests/unit/test_core/test_datastore.py
pyoneai/tests/unit/test_core/test_group.py
pyoneai/tests/unit/test_core/test_host.py
pyoneai/tests/unit/test_core/test_image.py
pyoneai/tests/unit/test_core/test_metric.py
pyoneai/tests/unit/test_core/test_metric_accessors.py
pyoneai/tests/unit/test_core/test_metric_collection.py
pyoneai/tests/unit/test_core/test_one.py
pyoneai/tests/unit/test_core/test_pci_device.py
pyoneai/tests/unit/test_core/test_predictor.py
pyoneai/tests/unit/test_core/test_service.py
pyoneai/tests/unit/test_core/test_time_index.py
pyoneai/tests/unit/test_core/test_user.py
pyoneai/tests/unit/test_core/test_virtual_machine.py
pyoneai-0.2.dist-info/LICENSE
pyoneai-0.2.dist-info/METADATA
pyoneai-0.2.dist-info/WHEEL
pyoneai-0.2.dist-info/top_level.txt
pyoneai-0.2.dist-info/RECORD
