Metadata-Version: 2.1
Name: pyoneai
Version: 0.2
Summary: OneAIOps SDK
Author-email: OpenNebula Systems <contact@opennebula.io>
Maintainer-email: OpenNebula Systems <contact@opennebula.io>
License:                                  Apache License
Project-URL: Source, https://github.com/OpenNebula/one-aiops
Project-URL: Bug Tracker, https://github.com/OpenNebula/one-aiops/issues
Project-URL: Wiki, https://github.com/OpenNebula/one-aiops/wiki
Keywords: AIOps,Cloud Computing,Machine Learning,Time seriers prediction,Anomaly detection
Classifier: Development Status :: 3 - Alpha
Classifier: Intended Audience :: Developers
Classifier: Topic :: Software Development :: Build Tools
Classifier: License :: OSI Approved :: Apache Software License
Classifier: Programming Language :: Python :: 3
Requires-Python: >=3.11
License-File: LICENSE
Requires-Dist: numpy<2,>=1.26
Requires-Dist: pandas<3,>=2.1
Requires-Dist: prometheus-api-client>=0.5
Requires-Dist: pydantic<2.9
Requires-Dist: pyyaml>=6.0
Requires-Dist: statsmodels>=0.14.2
Provides-Extra: dev
Requires-Dist: black; extra == "dev"
Requires-Dist: isort; extra == "dev"
Requires-Dist: pytest; extra == "dev"
Requires-Dist: pytest-mock; extra == "dev"
Provides-Extra: ml
Requires-Dist: lightning<2.3.0,>=2.2.5; extra == "ml"
Requires-Dist: joblib>=1.4.2; extra == "ml"
